substrate_interface-1.8.0.dist-info/licenses/LICENSE
substrateinterface/__init__.py
substrateinterface/base.py
substrateinterface/constants.py
substrateinterface/contracts.py
substrateinterface/exceptions.py
substrateinterface/extensions.py
substrateinterface/interfaces.py
substrateinterface/key.py
substrateinterface/keypair.py
substrateinterface/storage.py
substrateinterface/data/chainspecs/ksmcc3.json
substrateinterface/data/chainspecs/ksmcc3_asset_hub.json
substrateinterface/data/chainspecs/ksmcc3_bridge_hub.json
substrateinterface/data/chainspecs/ksmcc3_coretime.json
substrateinterface/data/chainspecs/ksmcc3_encointer.json
substrateinterface/data/chainspecs/ksmcc3_people.json
substrateinterface/data/chainspecs/kusama.json
substrateinterface/data/chainspecs/paseo.json
substrateinterface/data/chainspecs/paseo_asset_hub.json
substrateinterface/data/chainspecs/paseo_coretime.json
substrateinterface/data/chainspecs/paseo_people.json
substrateinterface/data/chainspecs/polkadot.json
substrateinterface/data/chainspecs/polkadot_asset_hub.json
substrateinterface/data/chainspecs/polkadot_bridge_hub.json
substrateinterface/data/chainspecs/polkadot_collectives.json
substrateinterface/data/chainspecs/polkadot_coretime.json
substrateinterface/data/chainspecs/polkadot_people.json
substrateinterface/data/chainspecs/rococo_v2_2.json
substrateinterface/data/chainspecs/rococo_v2_2_asset_hub.json
substrateinterface/data/chainspecs/rococo_v2_2_bridge_hub.json
substrateinterface/data/chainspecs/rococo_v2_2_people.json
substrateinterface/data/chainspecs/westend2.json
substrateinterface/data/chainspecs/westend2_asset_hub.json
substrateinterface/data/chainspecs/westend2_bridge_hub.json
substrateinterface/data/chainspecs/westend2_collectives.json
substrateinterface/data/chainspecs/westend2_coretime.json
substrateinterface/data/chainspecs/westend2_people.json
substrateinterface/transport/__init__.py
substrateinterface/transport/base.py
substrateinterface/transport/http.py
substrateinterface/transport/smoldot.py
substrate_interface-1.8.0.dist-info/METADATA
substrate_interface-1.8.0.dist-info/WHEEL
substrate_interface-1.8.0.dist-info/top_level.txt
substrate_interface-1.8.0.dist-info/RECORD
