Metadata-Version: 2.4
Name: substrate-interface
Version: 1.8.0
Summary: Library for interfacing with a Substrate node
Home-page: https://github.com/polkascan/py-substrate-interface
Author: Stichting Polkascan (Polkascan Foundation)
Author-email: info@polkascan.org
Keywords: interface polkascan polkadot substrate blockchain rpc kusama
Classifier: Development Status :: 5 - Production/Stable
Classifier: Intended Audience :: Developers
Classifier: License :: OSI Approved :: Apache Software License
Classifier: Programming Language :: Python :: 3
Classifier: Programming Language :: Python :: 3.7
Classifier: Programming Language :: Python :: 3.8
Classifier: Programming Language :: Python :: 3.9
Classifier: Programming Language :: Python :: 3.10
Classifier: Programming Language :: Python :: 3.11
Requires-Python: >=3.7, <4
License-File: LICENSE
Requires-Dist: websocket-client<2,>=0.57.0
Requires-Dist: base58<3,>=1.0.3
Requires-Dist: certifi>=2019.3.9
Requires-Dist: idna<4,>=2.1.0
Requires-Dist: requests<3,>=2.21.0
Requires-Dist: xxhash<4,>=1.3.0
Requires-Dist: ecdsa<1,>=0.17.0
Requires-Dist: eth-keys<1,>=0.2.1
Requires-Dist: eth_utils<6,>=1.3.0
Requires-Dist: pycryptodome<4,>=3.11.0
Requires-Dist: PyNaCl<2,>=1.0.1
Requires-Dist: scalecodec<1.3,>=1.2.10
Requires-Dist: py-sr25519-bindings<1,>=0.2.0
Requires-Dist: py-ed25519-zebra-bindings<2,>=1.0
Requires-Dist: py-bip39-bindings<1,>=0.1.9
Requires-Dist: smoldot-light<1,>=0.1.0
Provides-Extra: test
Requires-Dist: coverage; extra == "test"
Requires-Dist: pytest; extra == "test"
Dynamic: author
Dynamic: author-email
Dynamic: classifier
Dynamic: description
Dynamic: description-content-type
Dynamic: home-page
Dynamic: keywords
Dynamic: license-file
Dynamic: provides-extra
Dynamic: requires-dist
Dynamic: requires-python
Dynamic: summary
